sphinx_blog/__init__.py
sphinx_blog/blog.py
sphinx_blog-0.0.1a12.dist-info/LICENSE.txt
sphinx_blog-0.0.1a12.dist-info/METADATA
sphinx_blog-0.0.1a12.dist-info/WHEEL
sphinx_blog-0.0.1a12.dist-info/top_level.txt
sphinx_blog-0.0.1a12.dist-info/RECORD
